dataimages/__about__.py
dataimages/__init__.py
dataimages-0.0.1.dist-info/METADATA
dataimages-0.0.1.dist-info/WHEEL
dataimages-0.0.1.dist-info/licenses/LICENSE.txt
dataimages-0.0.1.dist-info/RECORD
