Metadata-Version: 2.1
Name: dataimages
Version: 0.0.1
Project-URL: Documentation, https://github.com/unknown/dataimages#readme
Project-URL: Issues, https://github.com/unknown/dataimages/issues
Project-URL: Source, https://github.com/unknown/dataimages
Author-email: Xavier Petit <nuxion@gmail.com>
License-File: LICENSE.txt
Classifier: Development Status :: 4 - Beta
Classifier: Programming Language :: Python
Classifier: Programming Language :: Python :: 3.7
Classifier: Programming Language :: Python :: 3.8
Classifier: Programming Language :: Python :: 3.9
Classifier: Programming Language :: Python :: 3.10
Classifier: Programming Language :: Python :: 3.11
Classifier: Programming Language :: Python :: Implementation :: CPython
Classifier: Programming Language :: Python :: Implementation :: PyPy
Requires-Python: >=3.7
